<annotation>
    <folder>naruto_training</folder>
    <filename>kakashi_47.jpg</filename>
    <size>
        <width>700</width>
        <height>393</height>
        <depth>3</depth>
    </size>
    <segmented>0</segmented>
    <object>
        <name>kakashi</name>
        <pose>Unspecified</pose>
        <truncated>0</truncated>
        <occluded>0</occluded>
        <difficult>0</difficult>
        <bndbox>
            <xmin>188</xmin>
            <ymin>68</ymin>
            <xmax>470</xmax>
            <ymax>385</ymax>
        </bndbox>
    </object>
</annotation>