<annotation>
    <folder>naruto_training</folder>
    <filename>mix_98.jpg</filename>
    <size>
        <width>512</width>
        <height>512</height>
        <depth>3</depth>
    </size>
    <segmented>0</segmented>
    <object>
        <name>sakura</name>
        <pose>Unspecified</pose>
        <truncated>0</truncated>
        <occluded>0</occluded>
        <difficult>0</difficult>
        <bndbox>
            <xmin>24</xmin>
            <ymin>95</ymin>
            <xmax>151</xmax>
            <ymax>258</ymax>
        </bndbox>
    </object>
    <object>
        <name>naruto</name>
        <pose>Unspecified</pose>
        <truncated>0</truncated>
        <occluded>0</occluded>
        <difficult>0</difficult>
        <bndbox>
            <xmin>307</xmin>
            <ymin>125</ymin>
            <xmax>448</xmax>
            <ymax>255</ymax>
        </bndbox>
    </object>
</annotation>